[
 {
   "id": 41002,
   "product-name": "Rugby 2004",
   "console-name": "PAL Playstation 2",
   "price-in-pennies": 152,
   "include-string": "Game, Box",
   "condition-string": "Normal wear",
   "sku": "",
   "description": "",
   "photos": ""
 },
 {
   "id": 38602,
   "product-name": "Link - Twilight Princess",
   "console-name": "Amiibo",
   "price-in-pennies": 3100,
   "include-string": "Figure only",
   "condition-string": "Normal wear",
   "sku": "",
   "description": "",
   "photos": ""
 },
 {
   "id": 64241,
   "product-name": "Mad Max",
   "console-name": "PAL Xbox One",
   "price-in-pennies": 816,
   "include-string": "Game, Box",
   "condition-string": "Normal wear",
   "sku": "",
   "description": "",
   "photos": ""
 },
 {
   "id": 59431,
   "product-name": "Spiderman 2",
   "console-name": "PAL Xbox",
   "price-in-pennies": 428,
   "include-string": "Game, Box",
   "condition-string": "Normal wear",
   "sku": "",
   "description": "",
   "photos": ""
 },
 {
   "id": 37433,
   "product-name": "Mario Kart 8 Deluxe",
   "console-name": "Nintendo Switch",
   "price-in-pennies": 4723,
   "include-string": "Game, Box",
   "condition-string": "Normal wear",
   "sku": "",
   "description": "",
   "photos": ""
 },
 {
   "id": 60079,
   "product-name": "Grand Theft Auto IV",
   "console-name": "PAL Xbox 360",
   "price-in-pennies": 825,
   "include-string": "Game, Box, Manual",
   "condition-string": "Normal wear",
   "sku": "",
   "description": "",
   "photos": ""
 },
 {
   "id": 45619,
   "product-name": "Time Splitters 2",
   "console-name": "PAL Gamecube",
   "price-in-pennies": 1416,
   "include-string": "Game, Box",
   "condition-string": "Normal wear",
   "sku": "",
   "description": "",
   "photos": ""
 },
 {
   "id": 60261,
   "product-name": "MX vs. ATV: Untamed",
   "console-name": "PAL Xbox 360",
   "price-in-pennies": 1017,
   "include-string": "Game, Box",
   "condition-string": "Normal wear",
   "sku": "",
   "description": "",
   "photos": ""
 },
 {
   "id": 60327,
   "product-name": "Nier",
   "console-name": "PAL Xbox 360",
   "price-in-pennies": 1697,
   "include-string": "Game, Box",
   "condition-string": "Normal wear",
   "sku": "",
   "description": "",
   "photos": ""
 },
 {
   "id": 64985,
   "product-name": "State of Decay 2",
   "console-name": "PAL Xbox One",
   "price-in-pennies": 642,
   "include-string": "Game, Box",
   "condition-string": "Normal wear",
   "sku": "",
   "description": "",
   "photos": ""
 },
 {
   "id": 63169,
   "product-name": "Super Mario Odyssey",
   "console-name": "PAL Nintendo Switch",
   "price-in-pennies": 4105,
   "include-string": "Game, Box",
   "condition-string": "Normal wear",
   "sku": "",
   "description": "",
   "photos": ""
 },
 {
   "id": 40042,
   "product-name": "Donkey Kong 64",
   "console-name": "PAL Nintendo 64",
   "price-in-pennies": 2717,
   "include-string": "Game only",
   "condition-string": "Normal wear",
   "sku": "",
   "description": "",
   "photos": ""
 },
 {
   "id": 60085,
   "product-name": "Grand Theft Auto: San Andreas",
   "console-name": "PAL Xbox 360",
   "price-in-pennies": 2103,
   "include-string": "Game, Box",
   "condition-string": "Normal wear",
   "sku": "",
   "description": "",
   "photos": ""
 },
 {
   "id": 59472,
   "product-name": "Forza Motorsport",
   "console-name": "PAL Xbox",
   "price-in-pennies": 302,
   "include-string": "Game, Box",
   "condition-string": "Normal wear",
   "sku": "",
   "description": "",
   "photos": ""
 },
 {
   "id": 60712,
   "product-name": "Gears of War: Judgment",
   "console-name": "PAL Xbox 360",
   "price-in-pennies": 315,
   "include-string": "Game, Box",
   "condition-string": "Normal wear",
   "sku": "",
   "description": "",
   "photos": ""
 },
 {
   "id": 58197,
   "product-name": "Young Link",
   "console-name": "Amiibo",
   "price-in-pennies": 2007,
   "include-string": "Figure only",
   "condition-string": "Normal wear",
   "sku": "",
   "description": "",
   "photos": ""
 },
 {
   "id": 60706,
   "product-name": "Forza Motorsport 4",
   "console-name": "PAL Xbox 360",
   "price-in-pennies": 693,
   "include-string": "Game, Box",
   "condition-string": "Normal wear",
   "sku": "",
   "description": "",
   "photos": ""
 },
 {
   "id": 35689,
   "product-name": "Inkling Boy",
   "console-name": "Amiibo",
   "price-in-pennies": 1499,
   "include-string": "Figure only",
   "condition-string": "Normal wear",
   "sku": "",
   "description": "",
   "photos": ""
 },
 {
   "id": 54057,
   "product-name": "Kingdom Hearts III [Deluxe Edition]",
   "console-name": "Xbox One",
   "price-in-pennies": 2269,
   "include-string": "Game, Box, Manual",
   "condition-string": "Normal wear",
   "sku": "",
   "description": "",
   "photos": ""
 },
 {
   "id": 59787,
   "product-name": "Army of Two",
   "console-name": "PAL Xbox 360",
   "price-in-pennies": 425,
   "include-string": "Game, Box",
   "condition-string": "Normal wear",
   "sku": "",
   "description": "",
   "photos": ""
 },
 {
   "id": 59828,
   "product-name": "BioShock 2",
   "console-name": "PAL Xbox 360",
   "price-in-pennies": 324,
   "include-string": "Game, Box",
   "condition-string": "Normal wear",
   "sku": "",
   "description": "",
   "photos": ""
 },
 {
   "id": 60039,
   "product-name": "Far Cry 2",
   "console-name": "PAL Xbox 360",
   "price-in-pennies": 331,
   "include-string": "Game, Box",
   "condition-string": "Normal wear",
   "sku": "",
   "description": "",
   "photos": ""
 },
 {
   "id": 54421,
   "product-name": "Super Famicom System",
   "console-name": "Super Famicom",
   "price-in-pennies": 5199,
   "include-string": "Console only",
   "condition-string": "Normal wear",
   "sku": "",
   "description": "",
   "photos": ""
 },
 {
   "id": 64868,
   "product-name": "Forza Motorsport 5",
   "console-name": "PAL Xbox One",
   "price-in-pennies": 899,
   "include-string": "Game, Box",
   "condition-string": "Normal wear",
   "sku": "",
   "description": "",
   "photos": ""
 },
 {
   "id": 33910,
   "product-name": "God of War Ascension",
   "console-name": "Playstation 3",
   "price-in-pennies": 1253,
   "include-string": "Game, Box",
   "condition-string": "Normal wear",
   "sku": "",
   "description": "",
   "photos": ""
 },
 {
   "id": 56718,
   "product-name": "Crisis Core: Final Fantasy VII",
   "console-name": "PAL PSP",
   "price-in-pennies": 1419,
   "include-string": "Game, Box",
   "condition-string": "Normal wear",
   "sku": "",
   "description": "",
   "photos": ""
 },
 {
   "id": 37954,
   "product-name": "Splatoon 2",
   "console-name": "Nintendo Switch",
   "price-in-pennies": 4385,
   "include-string": "Game, Box",
   "condition-string": "Normal wear",
   "sku": "",
   "description": "",
   "photos": ""
 },
 {
   "id": 35411,
   "product-name": "Pokemon Alpha Sapphire",
   "console-name": "Nintendo 3DS",
   "price-in-pennies": 2643,
   "include-string": "Game, Box",
   "condition-string": "Normal wear",
   "sku": "",
   "description": "",
   "photos": ""
 },
 {
   "id": 60639,
   "product-name": "Borderlands 2",
   "console-name": "PAL Xbox 360",
   "price-in-pennies": 390,
   "include-string": "Game, Box",
   "condition-string": "Normal wear",
   "sku": "",
   "description": "",
   "photos": ""
 },
 {
   "id": 35151,
   "product-name": "Super Smash Bros for Nintendo 3DS",
   "console-name": "Nintendo 3DS",
   "price-in-pennies": 1366,
   "include-string": "Game, Box",
   "condition-string": "Normal wear",
   "sku": "",
   "description": "",
   "photos": ""
 },
 {
   "id": 60761,
   "product-name": "Lost Planet: Extreme Condition",
   "console-name": "PAL Xbox 360",
   "price-in-pennies": 322,
   "include-string": "Game, Box",
   "condition-string": "Normal wear",
   "sku": "",
   "description": "",
   "photos": ""
 },
 {
   "id": 48130,
   "product-name": "Uncharted Drake's Fortune",
   "console-name": "PAL Playstation 3",
   "price-in-pennies": 344,
   "include-string": "Game, Box",
   "condition-string": "Normal wear",
   "sku": "",
   "description": "",
   "photos": ""
 },
 {
   "id": 40749,
   "product-name": "Burnout 3 Takedown",
   "console-name": "PAL Playstation 2",
   "price-in-pennies": 557,
   "include-string": "Game, Box",
   "condition-string": "Normal wear",
   "sku": "",
   "description": "",
   "photos": ""
 },
 {
   "id": 57416,
   "product-name": "God of War",
   "console-name": "PAL Playstation 4",
   "price-in-pennies": 1254,
   "include-string": "Game only",
   "condition-string": "Normal wear",
   "sku": "",
   "description": "",
   "photos": ""
 },
 {
   "id": 59016,
   "product-name": "Metal Arms: Glitch in the System",
   "console-name": "PAL Xbox",
   "price-in-pennies": 621,
   "include-string": "Game, Box",
   "condition-string": "Normal wear",
   "sku": "",
   "description": "",
   "photos": ""
 },
 {
   "id": 40748,
   "product-name": "Burnout 2 Point of Impact",
   "console-name": "PAL Playstation 2",
   "price-in-pennies": 378,
   "include-string": "Game, Box",
   "condition-string": "Normal wear",
   "sku": "",
   "description": "",
   "photos": ""
 },
 {
   "id": 2986,
   "product-name": "Pokemon Silver",
   "console-name": "GameBoy Color",
   "price-in-pennies": 2063,
   "include-string": "Game only",
   "condition-string": "Normal wear",
   "sku": "",
   "description": "",
   "photos": ""
 },
 {
   "id": 60075,
   "product-name": "Gears of War",
   "console-name": "PAL Xbox 360",
   "price-in-pennies": 321,
   "include-string": "Game, Box",
   "condition-string": "Normal wear",
   "sku": "",
   "description": "",
   "photos": ""
 },
 {
   "id": 40714,
   "product-name": "Bionicle Heroes",
   "console-name": "PAL Playstation 2",
   "price-in-pennies": 274,
   "include-string": "Game, Box",
   "condition-string": "Normal wear",
   "sku": "",
   "description": "",
   "photos": ""
 },
 {
   "id": 64180,
   "product-name": "Fallout 4",
   "console-name": "PAL Xbox One",
   "price-in-pennies": 478,
   "include-string": "Game, Box",
   "condition-string": "Normal wear",
   "sku": "",
   "description": "",
   "photos": ""
 },
 {
   "id": 59460,
   "product-name": "Brothers in Arms: Road to Hill 30",
   "console-name": "PAL Xbox",
   "price-in-pennies": 327,
   "include-string": "Game, Box",
   "condition-string": "Normal wear",
   "sku": "",
   "description": "",
   "photos": ""
 },
 {
   "id": 16877,
   "product-name": "Game Boy Color Yellow",
   "console-name": "GameBoy Color",
   "price-in-pennies": 4500,
   "include-string": "Console only",
   "condition-string": "Normal wear",
   "sku": "",
   "description": "",
   "photos": ""
 },
 {
   "id": 40054,
   "product-name": "F1 World Grand Prix",
   "console-name": "PAL Nintendo 64",
   "price-in-pennies": 321,
   "include-string": "Game only",
   "condition-string": "Normal wear",
   "sku": "",
   "description": "",
   "photos": ""
 },
 {
   "id": 48128,
   "product-name": "Uncharted 2: Among Thieves",
   "console-name": "PAL Playstation 3",
   "price-in-pennies": 360,
   "include-string": "Game, Box",
   "condition-string": "Normal wear",
   "sku": "",
   "description": "",
   "photos": ""
 },
 {
   "id": 2285,
   "product-name": "Kingdom Hearts Chain of Memories",
   "console-name": "GameBoy Advance",
   "price-in-pennies": 781,
   "include-string": "Game only",
   "condition-string": "Normal wear",
   "sku": "",
   "description": "",
   "photos": ""
 },
 {
   "id": 59792,
   "product-name": "Assassin's Creed II",
   "console-name": "PAL Xbox 360",
   "price-in-pennies": 305,
   "include-string": "Game, Box",
   "condition-string": "Normal wear",
   "sku": "",
   "description": "",
   "photos": ""
 },
 {
   "id": 41390,
   "product-name": "LEGO Star Wars",
   "console-name": "PAL Playstation 2",
   "price-in-pennies": 373,
   "include-string": "Game, Box",
   "condition-string": "Normal wear",
   "sku": "",
   "description": "",
   "photos": ""
 },
 {
   "id": 60108,
   "product-name": "Halo: Reach",
   "console-name": "PAL Xbox 360",
   "price-in-pennies": 379,
   "include-string": "Game, Box",
   "condition-string": "Normal wear",
   "sku": "",
   "description": "",
   "photos": ""
 },
 {
   "id": 63419,
   "product-name": "Your Shape: Fitness Evolved 2013",
   "console-name": "PAL Wii U",
   "price-in-pennies": 935,
   "include-string": "Game, Box",
   "condition-string": "Normal wear",
   "sku": "",
   "description": "",
   "photos": ""
 },
 {
   "id": 45430,
   "product-name": "Metroid Prime",
   "console-name": "PAL Gamecube",
   "price-in-pennies": 1654,
   "include-string": "Game, Box",
   "condition-string": "Normal wear",
   "sku": "",
   "description": "",
   "photos": ""
 },
 {
   "id": 34410,
   "product-name": "Skylanders Swap Force: Starter Pack",
   "console-name": "Wii U",
   "price-in-pennies": 1797,
   "include-string": "Game, Box, Manual",
   "condition-string": "Normal wear",
   "sku": "",
   "description": "",
   "photos": ""
 },
 {
   "id": 45261,
   "product-name": "Burnout",
   "console-name": "PAL Gamecube",
   "price-in-pennies": 557,
   "include-string": "Game, Box",
   "condition-string": "Normal wear",
   "sku": "",
   "description": "",
   "photos": ""
 },
 {
   "id": 41536,
   "product-name": "MX vs. ATV Unleashed",
   "console-name": "PAL Playstation 2",
   "price-in-pennies": 398,
   "include-string": "Game, Box",
   "condition-string": "Normal wear",
   "sku": "",
   "description": "",
   "photos": ""
 },
 {
   "id": 41468,
   "product-name": "Metal Gear Solid 2",
   "console-name": "PAL Playstation 2",
   "price-in-pennies": 481,
   "include-string": "Game, Box",
   "condition-string": "Normal wear",
   "sku": "",
   "description": "",
   "photos": ""
 },
 {
   "id": 60661,
   "product-name": "Dead Island: Riptide",
   "console-name": "PAL Xbox 360",
   "price-in-pennies": 346,
   "include-string": "Game, Box",
   "condition-string": "Normal wear",
   "sku": "",
   "description": "",
   "photos": ""
 },
 {
   "id": 60774,
   "product-name": "Metal Gear Solid HD Collection",
   "console-name": "PAL Xbox 360",
   "price-in-pennies": 1857,
   "include-string": "Game, Box",
   "condition-string": "Normal wear",
   "sku": "",
   "description": "",
   "photos": ""
 },
 {
   "id": 38603,
   "product-name": "Link - Majora's Mask",
   "console-name": "Amiibo",
   "price-in-pennies": 2191,
   "include-string": "Figure only",
   "condition-string": "Normal wear",
   "sku": "",
   "description": "",
   "photos": ""
 },
 {
   "id": 33034,
   "product-name": "Nintendo 3DS XL Black & Blue",
   "console-name": "Nintendo 3DS",
   "price-in-pennies": 10562,
   "include-string": "Console only",
   "condition-string": "Normal wear",
   "sku": "",
   "description": "",
   "photos": ""
 },
 {
   "id": 59830,
   "product-name": "BioShock Infinite",
   "console-name": "PAL Xbox 360",
   "price-in-pennies": 375,
   "include-string": "Game, Box",
   "condition-string": "Normal wear",
   "sku": "",
   "description": "",
   "photos": ""
 },
 {
   "id": 6780,
   "product-name": "Xbox 360 System Elite 120GB",
   "console-name": "Xbox 360",
   "price-in-pennies": 5012,
   "include-string": "Console only",
   "condition-string": "Normal wear",
   "sku": "",
   "description": "",
   "photos": ""
 },
 {
   "id": 60381,
   "product-name": "Red Faction: Guerrilla",
   "console-name": "PAL Xbox 360",
   "price-in-pennies": 279,
   "include-string": "Game, Box",
   "condition-string": "Normal wear",
   "sku": "",
   "description": "",
   "photos": ""
 },
 {
   "id": 37760,
   "product-name": "ARMS",
   "console-name": "Nintendo Switch",
   "price-in-pennies": 5056,
   "include-string": "Game, Box",
   "condition-string": "Normal wear",
   "sku": "",
   "description": "",
   "photos": ""
 },
 {
   "id": 40716,
   "product-name": "Black",
   "console-name": "PAL Playstation 2",
   "price-in-pennies": 699,
   "include-string": "Game, Box",
   "condition-string": "Normal wear",
   "sku": "",
   "description": "",
   "photos": ""
 },
 {
   "id": 33364,
   "product-name": "Wii U Console Basic White 8GB",
   "console-name": "Wii U",
   "price-in-pennies": 16349,
   "include-string": "Console, Box",
   "condition-string": "Normal wear",
   "sku": "",
   "description": "",
   "photos": ""
 },
 {
   "id": 3974,
   "product-name": "Yellow Controller",
   "console-name": "Nintendo 64",
   "price-in-pennies": 2439,
   "include-string": "Controller only",
   "condition-string": "Normal wear",
   "sku": "",
   "description": "",
   "photos": ""
 },
 {
   "id": 14830,
   "product-name": "Elder Scrolls III Morrowind [Game of the Year]",
   "console-name": "Xbox",
   "price-in-pennies": 1921,
   "include-string": "Game, Box",
   "condition-string": "Normal wear",
   "sku": "",
   "description": "",
   "photos": ""
 },
 {
   "id": 64863,
   "product-name": "FIFA 19",
   "console-name": "PAL Xbox One",
   "price-in-pennies": 530,
   "include-string": "Game, Box",
   "condition-string": "Normal wear",
   "sku": "",
   "description": "",
   "photos": ""
 },
 {
   "id": 37294,
   "product-name": "Zelda Breath of the Wild",
   "console-name": "Nintendo Switch",
   "price-in-pennies": 4450,
   "include-string": "Game, Box",
   "condition-string": "Normal wear",
   "sku": "",
   "description": "",
   "photos": ""
 },
 {
   "id": 35705,
   "product-name": "State of Decay: Year-One Survival Edition",
   "console-name": "Xbox One",
   "price-in-pennies": 967,
   "include-string": "Game, Box",
   "condition-string": "Normal wear",
   "sku": "",
   "description": "",
   "photos": ""
 },
 {
   "id": 40906,
   "product-name": "Devil May Cry 3",
   "console-name": "PAL Playstation 2",
   "price-in-pennies": 431,
   "include-string": "Game, Box",
   "condition-string": "Normal wear",
   "sku": "",
   "description": "",
   "photos": ""
 },
 {
   "id": 40185,
   "product-name": "Star Wars Episode I Racer",
   "console-name": "PAL Nintendo 64",
   "price-in-pennies": 896,
   "include-string": "Game only",
   "condition-string": "Normal wear",
   "sku": "",
   "description": "",
   "photos": ""
 },
 {
   "id": 6736,
   "product-name": "Xbox System",
   "console-name": "Xbox",
   "price-in-pennies": 4411,
   "include-string": "Console only",
   "condition-string": "Normal wear",
   "sku": "",
   "description": "",
   "photos": ""
 },
 {
   "id": 41354,
   "product-name": "Kingdom Hearts",
   "console-name": "PAL Playstation 2",
   "price-in-pennies": 893,
   "include-string": "Game, Box, Manual",
   "condition-string": "Normal wear",
   "sku": "",
   "description": "",
   "photos": ""
 },
 {
   "id": 37396,
   "product-name": "Link - Rider",
   "console-name": "Amiibo",
   "price-in-pennies": 1925,
   "include-string": "Figure only",
   "condition-string": "Normal wear",
   "sku": "",
   "description": "",
   "photos": ""
 },
 {
   "id": 64201,
   "product-name": "Halo 5 Guardians",
   "console-name": "PAL Xbox One",
   "price-in-pennies": 579,
   "include-string": "Game, Box",
   "condition-string": "Normal wear",
   "sku": "",
   "description": "",
   "photos": ""
 },
 {
   "id": 14865,
   "product-name": "Xbox 360 Console Premium 60GB",
   "console-name": "Xbox 360",
   "price-in-pennies": 8338,
   "include-string": "Console, Box",
   "condition-string": "Normal wear",
   "sku": "",
   "description": "",
   "photos": ""
 },
 {
   "id": 36483,
   "product-name": "Zelda Twilight Princess HD [amiibo Bundle]",
   "console-name": "Wii U",
   "price-in-pennies": 5463,
   "include-string": "Game, Box",
   "condition-string": "Normal wear",
   "sku": "",
   "description": "",
   "photos": ""
 },
 {
   "id": 64503,
   "product-name": "Crash Bandicoot N. Sane Trilogy",
   "console-name": "PAL Nintendo Switch",
   "price-in-pennies": 2559,
   "include-string": "Game, Box",
   "condition-string": "Normal wear",
   "sku": "",
   "description": "",
   "photos": ""
 },
 {
   "id": 60462,
   "product-name": "Splinter Cell: Double Agent",
   "console-name": "PAL Xbox 360",
   "price-in-pennies": 362,
   "include-string": "Game, Box, Manual",
   "condition-string": "Torn label",
   "sku": "",
   "description": "",
   "photos": ""
 },
 {
   "id": 63332,
   "product-name": "Just Dance 2016",
   "console-name": "PAL Wii U",
   "price-in-pennies": 913,
   "include-string": "Game, Box",
   "condition-string": "Normal wear",
   "sku": "",
   "description": "",
   "photos": ""
 },
 {
   "id": 45429,
   "product-name": "Metal Gear Solid Twin Snakes",
   "console-name": "PAL Gamecube",
   "price-in-pennies": 7259,
   "include-string": "Game, Box, Manual",
   "condition-string": "Normal wear",
   "sku": "",
   "description": "",
   "photos": ""
 },
 {
   "id": 13899,
   "product-name": "Metal Gear Solid 4 Guns of the Patriots",
   "console-name": "Playstation 3",
   "price-in-pennies": 737,
   "include-string": "Game, Box",
   "condition-string": "Normal wear",
   "sku": "",
   "description": "",
   "photos": ""
 },
 {
   "id": 40004,
   "product-name": "Automobili Lamborghini",
   "console-name": "PAL Nintendo 64",
   "price-in-pennies": 534,
   "include-string": "Game only",
   "condition-string": "Normal wear",
   "sku": "",
   "description": "",
   "photos": ""
 },
 {
   "id": 11191,
   "product-name": "Wario Ware Smooth Moves",
   "console-name": "Wii",
   "price-in-pennies": 1633,
   "include-string": "Game, Box",
   "condition-string": "Normal wear",
   "sku": "",
   "description": "",
   "photos": ""
 },
 {
   "id": 63961,
   "product-name": "Super Smash Bros. Ultimate",
   "console-name": "PAL Nintendo Switch",
   "price-in-pennies": 4428,
   "include-string": "Game, Box",
   "condition-string": "Normal wear",
   "sku": "",
   "description": "",
   "photos": ""
 },
 {
   "id": 45375,
   "product-name": "007 Agent Under Fire",
   "console-name": "PAL Gamecube",
   "price-in-pennies": 508,
   "include-string": "Game, Box",
   "condition-string": "Normal wear",
   "sku": "",
   "description": "",
   "photos": ""
 },
 {
   "id": 60019,
   "product-name": "Fable Anniversary",
   "console-name": "PAL Xbox 360",
   "price-in-pennies": 1850,
   "include-string": "Game, Box",
   "condition-string": "Normal wear",
   "sku": "",
   "description": "",
   "photos": ""
 },
 {
   "id": 40092,
   "product-name": "Lylat Wars",
   "console-name": "PAL Nintendo 64",
   "price-in-pennies": 1074,
   "include-string": "Game only",
   "condition-string": "Normal wear",
   "sku": "",
   "description": "",
   "photos": ""
 },
 {
   "id": 21372,
   "product-name": "Ice Blue Nintendo DS Lite Limited Edition",
   "console-name": "Nintendo DS",
   "price-in-pennies": 7275,
   "include-string": "Console only",
   "condition-string": "Normal wear",
   "sku": "",
   "description": "",
   "photos": ""
 },
 {
   "id": 64847,
   "product-name": "Destiny",
   "console-name": "PAL Xbox One",
   "price-in-pennies": 272,
   "include-string": "Game, Box",
   "condition-string": "Normal wear",
   "sku": "",
   "description": "",
   "photos": ""
 },
 {
   "id": 13780,
   "product-name": "Playstation 3 System 80GB",
   "console-name": "Playstation 3",
   "price-in-pennies": 7207,
   "include-string": "Console only",
   "condition-string": "Normal wear",
   "sku": "",
   "description": "",
   "photos": ""
 },
 {
   "id": 56230,
   "product-name": "Pokemon Emerald",
   "console-name": "PAL GameBoy Advance",
   "price-in-pennies": 3576,
   "include-string": "Game only",
   "condition-string": "Normal wear",
   "sku": "",
   "description": "",
   "photos": ""
 },
 {
   "id": 60329,
   "product-name": "Orange Box",
   "console-name": "PAL Xbox 360",
   "price-in-pennies": 1469,
   "include-string": "Game, Box",
   "condition-string": "Normal wear",
   "sku": "",
   "description": "",
   "photos": ""
 },
 {
   "id": 60242,
   "product-name": "Metro: Last Light",
   "console-name": "PAL Xbox 360",
   "price-in-pennies": 423,
   "include-string": "Game, Box",
   "condition-string": "Normal wear",
   "sku": "",
   "description": "",
   "photos": ""
 },
 {
   "id": 64445,
   "product-name": "Wolfenstein: The New Order",
   "console-name": "PAL Xbox One",
   "price-in-pennies": 598,
   "include-string": "Game, Box",
   "condition-string": "Normal wear",
   "sku": "",
   "description": "",
   "photos": ""
 },
 {
   "id": 41870,
   "product-name": "The Simpsons Hit and Run",
   "console-name": "PAL Playstation 2",
   "price-in-pennies": 1374,
   "include-string": "Game, Box",
   "condition-string": "Normal wear",
   "sku": "",
   "description": "",
   "photos": ""
 },
 {
   "id": 47842,
   "product-name": "Resistance 3",
   "console-name": "PAL Playstation 3",
   "price-in-pennies": 535,
   "include-string": "Game, Box",
   "condition-string": "Normal wear",
   "sku": "",
   "description": "",
   "photos": ""
 },
 {
   "id": 41061,
   "product-name": "Eye Toy Play 2",
   "console-name": "PAL Playstation 2",
   "price-in-pennies": 226,
   "include-string": "Game, Box",
   "condition-string": "Normal wear",
   "sku": "",
   "description": "",
   "photos": ""
 },
 {
   "id": 4100,
   "product-name": "New Super Mario Bros",
   "console-name": "Nintendo DS",
   "price-in-pennies": 1453,
   "include-string": "Game, Box",
   "condition-string": "Normal wear",
   "sku": "",
   "description": "",
   "photos": ""
 },
 {
   "id": 59935,
   "product-name": "Dark Souls",
   "console-name": "PAL Xbox 360",
   "price-in-pennies": 927,
   "include-string": "Game, Box",
   "condition-string": "Normal wear",
   "sku": "",
   "description": "",
   "photos": ""
 },
 {
   "id": 59796,
   "product-name": "Assassin's Creed III",
   "console-name": "PAL Xbox 360",
   "price-in-pennies": 322,
   "include-string": "Game, Box",
   "condition-string": "Normal wear",
   "sku": "",
   "description": "",
   "photos": ""
 },
 {
   "id": 41958,
   "product-name": "SSX On Tour",
   "console-name": "PAL Playstation 2",
   "price-in-pennies": 355,
   "include-string": "Game, Box",
   "condition-string": "Normal wear",
   "sku": "",
   "description": "",
   "photos": ""
 },
 {
   "id": 45541,
   "product-name": "Soul Calibur II",
   "console-name": "PAL Gamecube",
   "price-in-pennies": 1064,
   "include-string": "Game, Box",
   "condition-string": "Normal wear",
   "sku": "",
   "description": "",
   "photos": ""
 },
 {
   "id": 47509,
   "product-name": "Heavy Rain",
   "console-name": "PAL Playstation 3",
   "price-in-pennies": 452,
   "include-string": "Game, Box",
   "condition-string": "Normal wear",
   "sku": "",
   "description": "",
   "photos": ""
 },
 {
   "id": 57199,
   "product-name": "Zelda Skyward Sword",
   "console-name": "PAL Wii",
   "price-in-pennies": 3571,
   "include-string": "Game, Box, Manual",
   "condition-string": "Normal wear",
   "sku": "",
   "description": "",
   "photos": ""
 },
 {
   "id": 63713,
   "product-name": "Snake",
   "console-name": "Amiibo",
   "price-in-pennies": 1471,
   "include-string": "Figure only",
   "condition-string": "Normal wear",
   "sku": "",
   "description": "",
   "photos": ""
 },
 {
   "id": 60106,
   "product-name": "Halo: Combat Evolved Anniversary",
   "console-name": "PAL Xbox 360",
   "price-in-pennies": 387,
   "include-string": "Game, Box",
   "condition-string": "Normal wear",
   "sku": "",
   "description": "",
   "photos": ""
 },
 {
   "id": 4122,
   "product-name": "Pokemon Diamond",
   "console-name": "Nintendo DS",
   "price-in-pennies": 3352,
   "include-string": "Game, Box",
   "condition-string": "Normal wear",
   "sku": "",
   "description": "",
   "photos": ""
 },
 {
   "id": 54890,
   "product-name": "Star Wars Battlefront: Elite Squadron",
   "console-name": "PAL PSP",
   "price-in-pennies": 834,
   "include-string": "Game, Box",
   "condition-string": "Normal wear",
   "sku": "",
   "description": "",
   "photos": ""
 },
 {
   "id": 63583,
   "product-name": "Until Dawn [Steelbook Edition]",
   "console-name": "PAL Playstation 4",
   "price-in-pennies": 3006,
   "include-string": "Game, Box",
   "condition-string": "Normal wear",
   "sku": "",
   "description": "",
   "photos": ""
 },
 {
   "id": 3552,
   "product-name": "Spiderman",
   "console-name": "Gamecube",
   "price-in-pennies": 797,
   "include-string": "Game, Box, Manual",
   "condition-string": "Normal wear",
   "sku": "",
   "description": "",
   "photos": ""
 },
 {
   "id": 36495,
   "product-name": "Donkey Kong Country Returns 3D [Nintendo Selects]",
   "console-name": "Nintendo 3DS",
   "price-in-pennies": 1311,
   "include-string": "Game, Box",
   "condition-string": "Normal wear",
   "sku": "",
   "description": "",
   "photos": ""
 },
 {
   "id": 31432,
   "product-name": "L.A. Noire",
   "console-name": "Xbox 360",
   "price-in-pennies": 556,
   "include-string": "Game, Box",
   "condition-string": "Normal wear",
   "sku": "",
   "description": "",
   "photos": ""
 },
 {
   "id": 35421,
   "product-name": "Diddy Kong",
   "console-name": "Amiibo",
   "price-in-pennies": 1497,
   "include-string": "Figure only",
   "condition-string": "Normal wear",
   "sku": "",
   "description": "",
   "photos": ""
 },
 {
   "id": 2631,
   "product-name": "The Incredible Hulk",
   "console-name": "GameBoy Advance",
   "price-in-pennies": 499,
   "include-string": "Game only",
   "condition-string": "Normal wear",
   "sku": "",
   "description": "",
   "photos": ""
 },
 {
   "id": 47545,
   "product-name": "Journey Collector's Edition",
   "console-name": "PAL Playstation 3",
   "price-in-pennies": 2015,
   "include-string": "Game, Box",
   "condition-string": "Normal wear",
   "sku": "",
   "description": "",
   "photos": ""
 },
 {
   "id": 59015,
   "product-name": "Mercenaries: Playground of Destruction",
   "console-name": "PAL Xbox",
   "price-in-pennies": 438,
   "include-string": "Game, Box",
   "condition-string": "Normal wear",
   "sku": "",
   "description": "",
   "photos": ""
 },
 {
   "id": 5773,
   "product-name": "Slim Playstation 2 System",
   "console-name": "Playstation 2",
   "price-in-pennies": 6189,
   "include-string": "Console only",
   "condition-string": "Normal wear",
   "sku": "",
   "description": "",
   "photos": ""
 },
 {
   "id": 63731,
   "product-name": "Link - Link's Awakening",
   "console-name": "Amiibo",
   "price-in-pennies": 1113,
   "include-string": "Figure only",
   "condition-string": "Normal wear",
   "sku": "",
   "description": "",
   "photos": ""
 },
 {
   "id": 54749,
   "product-name": "Kingdom Hearts Birth by Sleep",
   "console-name": "PAL PSP",
   "price-in-pennies": 1259,
   "include-string": "Game, Box, Manual",
   "condition-string": "Normal wear",
   "sku": "",
   "description": "",
   "photos": ""
 },
 {
   "id": 47529,
   "product-name": "Infamous",
   "console-name": "PAL Playstation 3",
   "price-in-pennies": 410,
   "include-string": "Game, Box",
   "condition-string": "Normal wear",
   "sku": "",
   "description": "",
   "photos": ""
 },
 {
   "id": 59803,
   "product-name": "Batman: Arkham Origins",
   "console-name": "PAL Xbox 360",
   "price-in-pennies": 796,
   "include-string": "Game, Box",
   "condition-string": "Normal wear",
   "sku": "",
   "description": "",
   "photos": ""
 },
 {
   "id": 19678,
   "product-name": "Kingdom Hearts 358/2 Days",
   "console-name": "Nintendo DS",
   "price-in-pennies": 1945,
   "include-string": "Game, Box",
   "condition-string": "Normal wear",
   "sku": "",
   "description": "",
   "photos": ""
 },
 {
   "id": 47841,
   "product-name": "Resistance 2",
   "console-name": "PAL Playstation 3",
   "price-in-pennies": 246,
   "include-string": "Game, Box",
   "condition-string": "Normal wear",
   "sku": "",
   "description": "",
   "photos": ""
 },
 {
   "id": 46460,
   "product-name": "Nintendo Switch 32GB Super Mario Odyssey Edition",
   "console-name": "Nintendo Switch",
   "price-in-pennies": 43845,
   "include-string": "Console, Box, Manual",
   "condition-string": "Normal wear",
   "sku": "",
   "description": "",
   "photos": ""
 },
 {
   "id": 41245,
   "product-name": "Harry Potter and the Goblet of Fire",
   "console-name": "PAL Playstation 2",
   "price-in-pennies": 342,
   "include-string": "Game, Box",
   "condition-string": "Normal wear",
   "sku": "",
   "description": "",
   "photos": ""
 },
 {
   "id": 35599,
   "product-name": "Devil May Cry: Definitive Edition",
   "console-name": "Xbox One",
   "price-in-pennies": 873,
   "include-string": "Game, Box",
   "condition-string": "Normal wear",
   "sku": "",
   "description": "",
   "photos": ""
 },
 {
   "id": 2405,
   "product-name": "Need for Speed Most Wanted",
   "console-name": "GameBoy Advance",
   "price-in-pennies": 552,
   "include-string": "Game only",
   "condition-string": "Normal wear",
   "sku": "",
   "description": "",
   "photos": ""
 },
 {
   "id": 41355,
   "product-name": "Kingdom Hearts 2",
   "console-name": "PAL Playstation 2",
   "price-in-pennies": 783,
   "include-string": "Game, Box, Manual",
   "condition-string": "Normal wear",
   "sku": "",
   "description": "",
   "photos": ""
 },
 {
   "id": 48564,
   "product-name": "Duke Nukem Time to Kill",
   "console-name": "PAL Playstation",
   "price-in-pennies": 714,
   "include-string": "Game, Box",
   "condition-string": "Normal wear",
   "sku": "",
   "description": "",
   "photos": ""
 },
 {
   "id": 56749,
   "product-name": "God of War: Chains of Olympus",
   "console-name": "PAL PSP",
   "price-in-pennies": 719,
   "include-string": "Game, Box",
   "condition-string": "Normal wear",
   "sku": "",
   "description": "",
   "photos": ""
 },
 {
   "id": 35300,
   "product-name": "Halo: The Master Chief Collection",
   "console-name": "Xbox One",
   "price-in-pennies": 2199,
   "include-string": "Game, Box",
   "condition-string": "Normal wear",
   "sku": "",
   "description": "",
   "photos": ""
 },
 {
   "id": 65195,
   "product-name": "Zelda Majora's Mask 3D",
   "console-name": "PAL Nintendo 3DS",
   "price-in-pennies": 3565,
   "include-string": "Game, Box",
   "condition-string": "Normal wear",
   "sku": "",
   "description": "",
   "photos": ""
 },
 {
   "id": 2212,
   "product-name": "Glacier Gameboy Advance System",
   "console-name": "GameBoy Advance",
   "price-in-pennies": 4569,
   "include-string": "Console only",
   "condition-string": "Normal wear",
   "sku": "",
   "description": "",
   "photos": ""
 },
 {
   "id": 2582,
   "product-name": "Star Wars The New Droid Army",
   "console-name": "GameBoy Advance",
   "price-in-pennies": 420,
   "include-string": "Game only",
   "condition-string": "Normal wear",
   "sku": "",
   "description": "",
   "photos": ""
 },
 {
   "id": 3141,
   "product-name": "Zelda Link's Awakening DX",
   "console-name": "GameBoy Color",
   "price-in-pennies": 2711,
   "include-string": "Game only",
   "condition-string": "Normal wear",
   "sku": "",
   "description": "",
   "photos": ""
 },
 {
   "id": 40190,
   "product-name": "Super Mario 64",
   "console-name": "PAL Nintendo 64",
   "price-in-pennies": 2054,
   "include-string": "Game only",
   "condition-string": "Normal wear",
   "sku": "",
   "description": "",
   "photos": ""
 },
 {
   "id": 60690,
   "product-name": "Fable III",
   "console-name": "PAL Xbox 360",
   "price-in-pennies": 674,
   "include-string": "Game, Box",
   "condition-string": "Normal wear",
   "sku": "",
   "description": "",
   "photos": ""
 },
 {
   "id": 14865,
   "product-name": "Xbox 360 Console Premium 60GB",
   "console-name": "Xbox 360",
   "price-in-pennies": 8008,
   "include-string": "Console only",
   "condition-string": "Normal wear",
   "sku": "",
   "description": "",
   "photos": ""
 },
 {
   "id": 5023,
   "product-name": "Black Dual Shock Controller",
   "console-name": "Playstation 2",
   "price-in-pennies": 1687,
   "include-string": "Controller, Box",
   "condition-string": "Normal wear",
   "sku": "",
   "description": "",
   "photos": ""
 },
 {
   "id": 37482,
   "product-name": "Playstation 4 1TB Slim Console",
   "console-name": "Playstation 4",
   "price-in-pennies": 23443,
   "include-string": "Console only",
   "condition-string": "Normal wear",
   "sku": "",
   "description": "",
   "photos": ""
 },
 {
   "id": 49572,
   "product-name": "WRC FIA World Rally Championship Arcade",
   "console-name": "PAL Playstation",
   "price-in-pennies": 512,
   "include-string": "Game, Box",
   "condition-string": "Normal wear",
   "sku": "",
   "description": "",
   "photos": ""
 },
 {
   "id": 60624,
   "product-name": "Assassin's Creed",
   "console-name": "PAL Xbox 360",
   "price-in-pennies": 438,
   "include-string": "Game, Box",
   "condition-string": "Normal wear",
   "sku": "",
   "description": "",
   "photos": ""
 },
 {
   "id": 63346,
   "product-name": "Zelda Wind Waker HD",
   "console-name": "PAL Wii U",
   "price-in-pennies": 2647,
   "include-string": "Game, Box",
   "condition-string": "Normal wear",
   "sku": "",
   "description": "",
   "photos": ""
 },
 {
   "id": 45440,
   "product-name": "MX Superfly",
   "console-name": "PAL Gamecube",
   "price-in-pennies": 509,
   "include-string": "Game, Box",
   "condition-string": "Normal wear",
   "sku": "",
   "description": "",
   "photos": ""
 },
 {
   "id": 14315,
   "product-name": "Zelda Ocarina of Time [Collector's Edition]",
   "console-name": "Nintendo 64",
   "price-in-pennies": 14015,
   "include-string": "Game, Box",
   "condition-string": "Normal wear",
   "sku": "",
   "description": "",
   "photos": ""
 },
 {
   "id": 47843,
   "product-name": "Resistance: Fall of Man",
   "console-name": "PAL Playstation 3",
   "price-in-pennies": 219,
   "include-string": "Game, Box",
   "condition-string": "Normal wear",
   "sku": "",
   "description": "",
   "photos": ""
 },
 {
   "id": 22173,
   "product-name": "Borderlands [Game of the Year]",
   "console-name": "Xbox 360",
   "price-in-pennies": 671,
   "include-string": "Game, Box",
   "condition-string": "Normal wear",
   "sku": "",
   "description": "",
   "photos": ""
 },
 {
   "id": 47526,
   "product-name": "Ico & Shadow of the Colossus Collection",
   "console-name": "PAL Playstation 3",
   "price-in-pennies": 1482,
   "include-string": "Game, Box",
   "condition-string": "Normal wear",
   "sku": "",
   "description": "",
   "photos": ""
 },
 {
   "id": 60773,
   "product-name": "Metal Gear Rising: Revengeance",
   "console-name": "PAL Xbox 360",
   "price-in-pennies": 446,
   "include-string": "Game, Box",
   "condition-string": "Normal wear",
   "sku": "",
   "description": "",
   "photos": ""
 },
 {
   "id": 38624,
   "product-name": "Pokemon HeartGold Version [Pokewalker]",
   "console-name": "Nintendo DS",
   "price-in-pennies": 18062,
   "include-string": "Game, Box, Manual",
   "condition-string": "Normal wear",
   "sku": "",
   "description": "",
   "photos": ""
 },
 {
   "id": 3691,
   "product-name": "Atomic Purple Controller",
   "console-name": "Nintendo 64",
   "price-in-pennies": 2300,
   "include-string": "Controller only",
   "condition-string": "Normal wear",
   "sku": "",
   "description": "",
   "photos": ""
 },
 {
   "id": 64273,
   "product-name": "Monster Hunter: World",
   "console-name": "PAL Xbox One",
   "price-in-pennies": 1031,
   "include-string": "Game, Box",
   "condition-string": "Normal wear",
   "sku": "",
   "description": "",
   "photos": ""
 },
 {
   "id": 63796,
   "product-name": "Zelda Link's Awakening [Limited Edition]",
   "console-name": "PAL Nintendo Switch",
   "price-in-pennies": 8866,
   "include-string": "Game, Box, Manual",
   "condition-string": "Normal wear",
   "sku": "",
   "description": "",
   "photos": ""
 },
 {
   "id": 59307,
   "product-name": "Halo: Combat Evolved",
   "console-name": "PAL Xbox",
   "price-in-pennies": 549,
   "include-string": "Game, Box",
   "condition-string": "Normal wear",
   "sku": "",
   "description": "",
   "photos": ""
 },
 {
   "id": 3858,
   "product-name": "Nintendo 64 System",
   "console-name": "Nintendo 64",
   "price-in-pennies": 9482,
   "include-string": "Console only",
   "condition-string": "Normal wear",
   "sku": "",
   "description": "",
   "photos": ""
 },
 {
   "id": 45292,
   "product-name": "Dave Mirra Freestyle BMX 2",
   "console-name": "PAL Gamecube",
   "price-in-pennies": 609,
   "include-string": "Game, Box",
   "condition-string": "Normal wear",
   "sku": "",
   "description": "",
   "photos": ""
 },
 {
   "id": 40767,
   "product-name": "Canis Canem Edit",
   "console-name": "PAL Playstation 2",
   "price-in-pennies": 812,
   "include-string": "Game, Box",
   "condition-string": "Normal wear",
   "sku": "",
   "description": "",
   "photos": ""
 },
 {
   "id": 9086,
   "product-name": "Halo 3 Limited Edition",
   "console-name": "Xbox 360",
   "price-in-pennies": 1914,
   "include-string": "Game, Box, Manual",
   "condition-string": "Normal wear",
   "sku": "",
   "description": "",
   "photos": ""
 },
 {
   "id": 60468,
   "product-name": "South Park: The Stick of Truth",
   "console-name": "PAL Xbox 360",
   "price-in-pennies": 375,
   "include-string": "Game only",
   "condition-string": "Normal wear",
   "sku": "",
   "description": "",
   "photos": ""
 },
 {
   "id": 37153,
   "product-name": "Super Mario Maker",
   "console-name": "Nintendo 3DS",
   "price-in-pennies": 1384,
   "include-string": "Game, Box",
   "condition-string": "Normal wear",
   "sku": "",
   "description": "",
   "photos": ""
 },
 {
   "id": 39330,
   "product-name": "Super Mario World",
   "console-name": "PAL Super Nintendo",
   "price-in-pennies": 1471,
   "include-string": "Game only",
   "condition-string": "Normal wear",
   "sku": "",
   "description": "",
   "photos": ""
 },
 {
   "id": 36744,
   "product-name": "Monster Hunter Generations",
   "console-name": "Nintendo 3DS",
   "price-in-pennies": 1023,
   "include-string": "Game, Box",
   "condition-string": "Normal wear",
   "sku": "",
   "description": "",
   "photos": ""
 },
 {
   "id": 60777,
   "product-name": "Minecraft",
   "console-name": "PAL Xbox 360",
   "price-in-pennies": 1944,
   "include-string": "Game, Box",
   "condition-string": "Normal wear",
   "sku": "",
   "description": "",
   "photos": ""
 },
 {
   "id": 59813,
   "product-name": "Battlefield: Bad Company",
   "console-name": "PAL Xbox 360",
   "price-in-pennies": 318,
   "include-string": "Game, Box",
   "condition-string": "Normal wear",
   "sku": "",
   "description": "",
   "photos": ""
 },
 {
   "id": 64198,
   "product-name": "Grand Theft Auto V",
   "console-name": "PAL Xbox One",
   "price-in-pennies": 1687,
   "include-string": "Game, Box, Manual",
   "condition-string": "Normal wear",
   "sku": "",
   "description": "",
   "photos": ""
 },
 {
   "id": 64328,
   "product-name": "Red Dead Redemption 2",
   "console-name": "PAL Xbox One",
   "price-in-pennies": 1995,
   "include-string": "Game, Box",
   "condition-string": "Normal wear",
   "sku": "",
   "description": "",
   "photos": ""
 },
 {
   "id": 57313,
   "product-name": "Bloodborne",
   "console-name": "PAL Playstation 4",
   "price-in-pennies": 1042,
   "include-string": "Game, Box",
   "condition-string": "Normal wear",
   "sku": "",
   "description": "",
   "photos": ""
 },
 {
   "id": 4080,
   "product-name": "Mario Kart DS",
   "console-name": "Nintendo DS",
   "price-in-pennies": 1300,
   "include-string": "Game, Box",
   "condition-string": "Normal wear",
   "sku": "",
   "description": "",
   "photos": ""
 },
 {
   "id": 47976,
   "product-name": "Starhawk",
   "console-name": "PAL Playstation 3",
   "price-in-pennies": 538,
   "include-string": "Game, Box",
   "condition-string": "Normal wear",
   "sku": "",
   "description": "",
   "photos": ""
 },
 {
   "id": 64446,
   "product-name": "Witcher 3: Wild Hunt",
   "console-name": "PAL Xbox One",
   "price-in-pennies": 1038,
   "include-string": "Game, Box",
   "condition-string": "Normal wear",
   "sku": "",
   "description": "",
   "photos": ""
 },
 {
   "id": 59921,
   "product-name": "Crysis 2",
   "console-name": "PAL Xbox 360",
   "price-in-pennies": 363,
   "include-string": "Game, Box",
   "condition-string": "Normal wear",
   "sku": "",
   "description": "",
   "photos": ""
 },
 {
   "id": 60202,
   "product-name": "Lord of the Rings: War in the North",
   "console-name": "PAL Xbox 360",
   "price-in-pennies": 655,
   "include-string": "Game, Box",
   "condition-string": "Normal wear",
   "sku": "",
   "description": "",
   "photos": ""
 },
 {
   "id": 60635,
   "product-name": "BioShock",
   "console-name": "PAL Xbox 360",
   "price-in-pennies": 407,
   "include-string": "Game, Box",
   "condition-string": "Normal wear",
   "sku": "",
   "description": "",
   "photos": ""
 },
 {
   "id": 31035,
   "product-name": "Pokemon White",
   "console-name": "Nintendo DS",
   "price-in-pennies": 4972,
   "include-string": "Game, Box",
   "condition-string": "Normal wear",
   "sku": "",
   "description": "",
   "photos": ""
 },
 {
   "id": 64194,
   "product-name": "Final Fantasy XV",
   "console-name": "PAL Xbox One",
   "price-in-pennies": 635,
   "include-string": "Game, Box",
   "condition-string": "Normal wear",
   "sku": "",
   "description": "",
   "photos": ""
 },
 {
   "id": 40040,
   "product-name": "Diddy Kong Racing",
   "console-name": "PAL Nintendo 64",
   "price-in-pennies": 1736,
   "include-string": "Game only",
   "condition-string": "Normal wear",
   "sku": "",
   "description": "",
   "photos": ""
 },
 {
   "id": 60741,
   "product-name": "Kane & Lynch: Dead Men",
   "console-name": "PAL Xbox 360",
   "price-in-pennies": 315,
   "include-string": "Game, Box",
   "condition-string": "Normal wear",
   "sku": "",
   "description": "",
   "photos": ""
 },
 {
   "id": 45466,
   "product-name": "NHL Hitz 2002",
   "console-name": "PAL Gamecube",
   "price-in-pennies": 702,
   "include-string": "Game, Box",
   "condition-string": "Normal wear",
   "sku": "",
   "description": "",
   "photos": ""
 },
 {
   "id": 45359,
   "product-name": "Harry Potter Chamber of Secrets",
   "console-name": "PAL Gamecube",
   "price-in-pennies": 545,
   "include-string": "Game, Box",
   "condition-string": "Normal wear",
   "sku": "",
   "description": "",
   "photos": ""
 },
 {
   "id": 57181,
   "product-name": "Super Smash Bros. Brawl",
   "console-name": "PAL Wii",
   "price-in-pennies": 1285,
   "include-string": "Game, Box",
   "condition-string": "Normal wear",
   "sku": "",
   "description": "",
   "photos": ""
 },
 {
   "id": 32792,
   "product-name": "Batman: Arkham City [Game of the Year]",
   "console-name": "Xbox 360",
   "price-in-pennies": 466,
   "include-string": "Game, Box",
   "condition-string": "Normal wear",
   "sku": "",
   "description": "",
   "photos": ""
 },
 {
   "id": 41266,
   "product-name": "Hitman 2",
   "console-name": "PAL Playstation 2",
   "price-in-pennies": 256,
   "include-string": "Game, Box",
   "condition-string": "Normal wear",
   "sku": "",
   "description": "",
   "photos": ""
 },
 {
   "id": 47467,
   "product-name": "God of War III",
   "console-name": "PAL Playstation 3",
   "price-in-pennies": 540,
   "include-string": "Game, Box",
   "condition-string": "Normal wear",
   "sku": "",
   "description": "",
   "photos": ""
 },
 {
   "id": 48034,
   "product-name": "Last of Us",
   "console-name": "PAL Playstation 3",
   "price-in-pennies": 1332,
   "include-string": "Game, Box",
   "condition-string": "Normal wear",
   "sku": "",
   "description": "",
   "photos": ""
 },
 {
   "id": 7503,
   "product-name": "Worms Open Warfare 2",
   "console-name": "Nintendo DS",
   "price-in-pennies": 1028,
   "include-string": "Game, Box",
   "condition-string": "Normal wear",
   "sku": "",
   "description": "",
   "photos": ""
 },
 {
   "id": 60853,
   "product-name": "Red Dead Redemption",
   "console-name": "PAL Xbox 360",
   "price-in-pennies": 919,
   "include-string": "Game, Box",
   "condition-string": "Normal wear",
   "sku": "",
   "description": "",
   "photos": ""
 },
 {
   "id": 48474,
   "product-name": "Crash Bandicoot 3 Warped",
   "console-name": "PAL Playstation",
   "price-in-pennies": 1081,
   "include-string": "Game only",
   "condition-string": "Normal wear",
   "sku": "",
   "description": "",
   "photos": ""
 },
 {
   "id": 59181,
   "product-name": "Star Wars Battlefront II",
   "console-name": "PAL Xbox",
   "price-in-pennies": 2152,
   "include-string": "Game, Box",
   "condition-string": "Normal wear",
   "sku": "",
   "description": "",
   "photos": ""
 },
 {
   "id": 2064,
   "product-name": "Cobalt Gameboy Advance SP",
   "console-name": "GameBoy Advance",
   "price-in-pennies": 6300,
   "include-string": "Console only",
   "condition-string": "Normal wear",
   "sku": "",
   "description": "",
   "photos": ""
 },
 {
   "id": 60620,
   "product-name": "Alan Wake",
   "console-name": "PAL Xbox 360",
   "price-in-pennies": 484,
   "include-string": "Game, Box",
   "condition-string": "Normal wear",
   "sku": "",
   "description": "",
   "photos": ""
 },
 {
   "id": 38871,
   "product-name": "Street Fighter II",
   "console-name": "PAL Super Nintendo",
   "price-in-pennies": 1418,
   "include-string": "Game only",
   "condition-string": "Normal wear",
   "sku": "",
   "description": "",
   "photos": ""
 },
 {
   "id": 40971,
   "product-name": "Madagascar",
   "console-name": "PAL Playstation 2",
   "price-in-pennies": 381,
   "include-string": "Game, Box",
   "condition-string": "Normal wear",
   "sku": "",
   "description": "",
   "photos": ""
 },
 {
   "id": 60629,
   "product-name": "Batman: Arkham Asylum",
   "console-name": "PAL Xbox 360",
   "price-in-pennies": 280,
   "include-string": "Game only",
   "condition-string": "Normal wear",
   "sku": "",
   "description": "",
   "photos": ""
 },
 {
   "id": 65235,
   "product-name": "Witcher 3 Wild Hunt Complete Edition",
   "console-name": "Nintendo Switch",
   "price-in-pennies": 3866,
   "include-string": "Game, Box, Manual",
   "condition-string": "Normal wear",
   "sku": "",
   "description": "",
   "photos": ""
 },
 {
   "id": 38613,
   "product-name": "Mario - Wedding",
   "console-name": "Amiibo",
   "price-in-pennies": 1231,
   "include-string": "Figure only",
   "condition-string": "Normal wear",
   "sku": "",
   "description": "",
   "photos": ""
 },
 {
   "id": 41729,
   "product-name": "Rayman Revolution",
   "console-name": "PAL Playstation 2",
   "price-in-pennies": 439,
   "include-string": "Game, Box",
   "condition-string": "Normal wear",
   "sku": "",
   "description": "",
   "photos": ""
 },
 {
   "id": 47431,
   "product-name": "The Darkness II",
   "console-name": "PAL Playstation 3",
   "price-in-pennies": 460,
   "include-string": "Game only",
   "condition-string": "Normal wear",
   "sku": "",
   "description": "",
   "photos": ""
 },
 {
   "id": 36496,
   "product-name": "Zelda Ocarina of Time 3D [Nintendo Selects]",
   "console-name": "Nintendo 3DS",
   "price-in-pennies": 1444,
   "include-string": "Game, Box",
   "condition-string": "Normal wear",
   "sku": "",
   "description": "",
   "photos": ""
 },
 {
   "id": 60299,
   "product-name": "Need for Speed: Most Wanted",
   "console-name": "PAL Xbox 360",
   "price-in-pennies": 729,
   "include-string": "Game, Box",
   "condition-string": "Normal wear",
   "sku": "",
   "description": "",
   "photos": ""
 },
 {
   "id": 3784,
   "product-name": "Green Controller",
   "console-name": "Nintendo 64",
   "price-in-pennies": 2078,
   "include-string": "Controller only",
   "condition-string": "Normal wear",
   "sku": "",
   "description": "",
   "photos": ""
 },
 {
   "id": 60060,
   "product-name": "Forza Motorsport 3",
   "console-name": "PAL Xbox 360",
   "price-in-pennies": 420,
   "include-string": "Game, Box",
   "condition-string": "Normal wear",
   "sku": "",
   "description": "",
   "photos": ""
 },
 {
   "id": 51803,
   "product-name": "Zelda Spirit Tracks",
   "console-name": "PAL Nintendo DS",
   "price-in-pennies": 2097,
   "include-string": "Game, Box",
   "condition-string": "Normal wear",
   "sku": "",
   "description": "",
   "photos": ""
 },
 {
   "id": 58791,
   "product-name": "Burnout Revenge",
   "console-name": "PAL Xbox",
   "price-in-pennies": 520,
   "include-string": "Game, Box",
   "condition-string": "Normal wear",
   "sku": "",
   "description": "",
   "photos": ""
 },
 {
   "id": 60689,
   "product-name": "Fable II",
   "console-name": "PAL Xbox 360",
   "price-in-pennies": 456,
   "include-string": "Game, Box",
   "condition-string": "Normal wear",
   "sku": "",
   "description": "",
   "photos": ""
 },
 {
   "id": 3190,
   "product-name": "Black GameCube System",
   "console-name": "Gamecube",
   "price-in-pennies": 6240,
   "include-string": "Console only",
   "condition-string": "Normal wear",
   "sku": "",
   "description": "",
   "photos": ""
 },
 {
   "id": 41921,
   "product-name": "Soul Calibur III",
   "console-name": "PAL Playstation 2",
   "price-in-pennies": 665,
   "include-string": "Game, Box",
   "condition-string": "Normal wear",
   "sku": "",
   "description": "",
   "photos": ""
 },
 {
   "id": 48129,
   "product-name": "Uncharted 3: Drake's Deception",
   "console-name": "PAL Playstation 3",
   "price-in-pennies": 258,
   "include-string": "Game only",
   "condition-string": "Normal wear",
   "sku": "",
   "description": "",
   "photos": ""
 },
 {
   "id": 60239,
   "product-name": "Medal of Honor: Airborne",
   "console-name": "PAL Xbox 360",
   "price-in-pennies": 450,
   "include-string": "Game, Box",
   "condition-string": "Normal wear",
   "sku": "",
   "description": "",
   "photos": ""
 },
 {
   "id": 58966,
   "product-name": "Halo 2",
   "console-name": "PAL Xbox",
   "price-in-pennies": 555,
   "include-string": "Game, Box",
   "condition-string": "Normal wear",
   "sku": "",
   "description": "",
   "photos": ""
 },
 {
   "id": 59963,
   "product-name": "Deadpool",
   "console-name": "PAL Xbox 360",
   "price-in-pennies": 769,
   "include-string": "Game, Box",
   "condition-string": "Normal wear",
   "sku": "",
   "description": "",
   "photos": ""
 },
 {
   "id": 56750,
   "product-name": "God of War: Ghost of Sparta",
   "console-name": "PAL PSP",
   "price-in-pennies": 1030,
   "include-string": "Game, Box",
   "condition-string": "Normal wear",
   "sku": "",
   "description": "",
   "photos": ""
 },
 {
   "id": 35183,
   "product-name": "Xbox One 500 GB Black Console",
   "console-name": "Xbox One",
   "price-in-pennies": 19091,
   "include-string": "Console, Box",
   "condition-string": "Normal wear",
   "sku": "",
   "description": "",
   "photos": ""
 },
 {
   "id": 49373,
   "product-name": "Emperor's New Groove",
   "console-name": "PAL Playstation",
   "price-in-pennies": 693,
   "include-string": "Game only",
   "condition-string": "Normal wear",
   "sku": "",
   "description": "",
   "photos": ""
 },
 {
   "id": 58330,
   "product-name": "Battlefield: Bad Company 2",
   "console-name": "PAL Xbox 360",
   "price-in-pennies": 311,
   "include-string": "Game, Box",
   "condition-string": "Normal wear",
   "sku": "",
   "description": "",
   "photos": ""
 },
 {
   "id": 3491,
   "product-name": "Purple and Clear Controller",
   "console-name": "Gamecube",
   "price-in-pennies": 2785,
   "include-string": "Controller only",
   "condition-string": "Normal wear",
   "sku": "",
   "description": "",
   "photos": ""
 },
 {
   "id": 32969,
   "product-name": "Kingdom Hearts 3D Dream Drop Distance",
   "console-name": "Nintendo 3DS",
   "price-in-pennies": 1342,
   "include-string": "Game, Box",
   "condition-string": "Normal wear",
   "sku": "",
   "description": "",
   "photos": ""
 },
 {
   "id": 40750,
   "product-name": "Burnout Revenge",
   "console-name": "PAL Playstation 2",
   "price-in-pennies": 442,
   "include-string": "Game, Box",
   "condition-string": "Normal wear",
   "sku": "",
   "description": "",
   "photos": ""
 },
 {
   "id": 59482,
   "product-name": "Brothers in Arms: Earned in Blood",
   "console-name": "PAL Xbox",
   "price-in-pennies": 325,
   "include-string": "Game, Box",
   "condition-string": "Normal wear",
   "sku": "",
   "description": "",
   "photos": ""
 },
 {
   "id": 57586,
   "product-name": "Star Wars Battlefront",
   "console-name": "PAL Playstation 4",
   "price-in-pennies": 559,
   "include-string": "Game, Box",
   "condition-string": "Normal wear",
   "sku": "",
   "description": "",
   "photos": ""
 }
]